uesgraphs/__init__.py
uesgraphs/uesgraph.py
uesgraphs/utilities.py
uesgraphs/visuals.py
uesgraphs/analyze/__init__.py
uesgraphs/analyze/data_handling/data_handling.py
uesgraphs/analyze/data_handling/graph_transformation.py
uesgraphs/analyze/data_handling/mat_handler.py
uesgraphs/data/Pinola_low_temp_network_inputs.mat
uesgraphs/data/campus_melaten.osm
uesgraphs/data/nodes.json
uesgraphs/data/only_heating.json
uesgraphs/data/uesgraphs_parameters_template.xlsx
uesgraphs/data/examples/demands-cool.csv
uesgraphs/data/examples/demands-dhw.csv
uesgraphs/data/examples/demands-heat.csv
uesgraphs/data/examples/ground_temps_hassel.csv
uesgraphs/data/examples/transurban_seestadt_uesgraphs.json
uesgraphs/data/examples/e15_geojson/buildings.geojson
uesgraphs/data/examples/e15_geojson/network.geojson
uesgraphs/data/examples/e15_geojson/supply.geojson
uesgraphs/data/pipe_catalogs/isoplus.csv
uesgraphs/data/templates/template_aixlib_components.json
uesgraphs/data/templates/template_components.json
uesgraphs/data/templates/inputs/template_input.txt
uesgraphs/data/templates/network/pipe_heat_loss.mako
uesgraphs/data/templates/network/annotations/diagram.mako
uesgraphs/data/templates/network/annotations/documentation.mako
uesgraphs/data/templates/network/annotations/experiment.mako
uesgraphs/data/templates/network/connections/output.mako
uesgraphs/data/templates/network/connections/supply_network.mako
uesgraphs/data/templates/network/demand/AixLib_Fluid_DistrictHeatingCooling_Demands_ClosedLoop_DHCSubstationHeatPumpChiller.mako
uesgraphs/data/templates/network/demand/AixLib_Fluid_DistrictHeatingCooling_Demands_ClosedLoop_DHCSubstationHeatPumpDirectCooling.mako
uesgraphs/data/templates/network/demand/AixLib_Fluid_DistrictHeatingCooling_Demands_OpenLoop_HeatPumpCarnot.mako
uesgraphs/data/templates/network/demand/AixLib_Fluid_DistrictHeatingCooling_Demands_OpenLoop_VarTSupplyDp.mako
uesgraphs-2.1.3.dist-info/licenses/LICENSE.md
uesgraphs-2.1.3.dist-info/METADATA
uesgraphs-2.1.3.dist-info/WHEEL
uesgraphs-2.1.3.dist-info/top_level.txt
uesgraphs-2.1.3.dist-info/RECORD
