Metadata-Version: 2.4
Name: uesgraphs
Version: 2.1.3
Summary: Automated graph-based simulation model generation and analysis tool
Author-email: Rahul Mohandasan Karuvingal <rahul.karuvingal@eonerc.rwth-aachen.de>
License: MIT
Project-URL: repository, https://github.com/RWTH-EBC/uesgraphs
Requires-Python: >=3.9
License-File: LICENSE.md
Requires-Dist: geopandas
Requires-Dist: networkx>=2.1
Requires-Dist: numpy
Requires-Dist: pandas
Requires-Dist: shapely
Requires-Dist: pyproj
Requires-Dist: matplotlib
Requires-Dist: scikit-learn
Requires-Dist: mako
Requires-Dist: dxfgrabber
Requires-Dist: seaborn
Requires-Dist: openpyxl
Requires-Dist: pyarrow
Requires-Dist: ipykernel
Requires-Dist: scipy
Requires-Dist: tomli>=1.2.0; python_version < "3.11"
Provides-Extra: dev
Requires-Dist: pyyaml; extra == "dev"
Requires-Dist: pytest>=6.0; extra == "dev"
Requires-Dist: pytest-mpl>=0.12; extra == "dev"
Requires-Dist: pytest-cov<5.0.0,>=4.0.0; extra == "dev"
Requires-Dist: coverage<8.0.0,>=7.0.0; extra == "dev"
Provides-Extra: modelica
Requires-Dist: OMPython>=3.4.0; extra == "modelica"
Dynamic: license-file
